[1,["06eORW0u9HEKg5JSX5AQGv","08euXolBdBYqZZ6X/NptGH","02delMVqdBD70a/HSD99FK","4fGNMeaHlNJp843HTwuxmc","3c3/6R2LJL1ZpYQExwXay9"],["_textureSetter"],["cc.SpriteFrame"],0,[[[{"name":"pop_result_05","rect":[0,0,613,105],"offset":[0,0],"originalSize":[613,105],"capInsets":[0,0,0,0]}],[0],0,[0],[0],[0]],[[{"name":"popmain_31","rect":[0,0,70,70],"offset":[0,0],"originalSize":[70,70],"capInsets":[0,0,0,0]}],[0],0,[0],[0],[1]],[[{"name":"default_sprite_splash","rect":[0,0,2,2],"offset":[0,0],"originalSize":[2,2],"capInsets":[0,0,0,0]}],[0],0,[0],[0],[2]],[[{"name":"pop_result_01","rect":[0,0,162,187],"offset":[0,0],"originalSize":[162,187],"capInsets":[26,29,30,60]}],[0],0,[0],[0],[3]],[[{"name":"pop_result_04","rect":[0,0,148,138],"offset":[0,0],"originalSize":[148,138],"capInsets":[11,7,10,23]}],[0],0,[0],[0],[4]]]]