[{"__type__":"cc.SpriteFrame","content":{"name":"btnGameSingle_hover_EN","texture":"c6Cz3Q30JGqbOgTBiuRvtL","rect":[0,338,281,44],"offset":[2,2],"originalSize":[301,70],"capInsets":[0,0,0,0]}},{"__type__":"cc.SpriteFrame","content":{"name":"rank_hover","texture":"c6Cz3Q30JGqbOgTBiuRvtL","rect":[361,374,76,72],"offset":[0,0],"originalSize":[82,82],"capInsets":[0,0,0,0]}},{"__type__":"cc.SpriteFrame","content":{"name":"btnWifiVS_EN","texture":"c6Cz3Q30JGqbOgTBiuRvtL","rect":[0,292,297,44],"offset":[0,2],"originalSize":[301,70],"capInsets":[0,0,0,0]}},{"__type__":"cc.SpriteFrame","content":{"name":"btnMusic","texture":"c6Cz3Q30JGqbOgTBiuRvtL","rect":[377,448,68,64],"offset":[0,-3],"originalSize":[80,80],"capInsets":[0,0,0,0]}},{"__type__":"cc.SpriteFrame","content":{"name":"btnSound_hover","texture":"c6Cz3Q30JGqbOgTBiuRvtL","rect":[305,448,70,64],"offset":[0,0],"originalSize":[80,80],"capInsets":[0,0,0,0]}},{"__type__":"cc.SpriteFrame","content":{"name":"game_title_CN","texture":"c6Cz3Q30JGqbOgTBiuRvtL","rect":[0,0,673,94],"offset":[0,1],"originalSize":[681,120],"capInsets":[0,0,0,0]}},{"__type__":"cc.Texture2D","content":"0,9729,9729,33071,33071,0,0,1"},{"__type__":"cc.SpriteFrame","content":{"name":"btnArrowRight","texture":"c6Cz3Q30JGqbOgTBiuRvtL","rect":[783,0,60,70],"offset":[0,0],"originalSize":[60,70],"capInsets":[0,0,0,0]}},{"__type__":"cc.SpriteFrame","content":{"name":"moregames","texture":"c6Cz3Q30JGqbOgTBiuRvtL","rect":[536,332,80,76],"offset":[0,0],"originalSize":[82,82],"capInsets":[0,0,0,0]}},{"__type__":"cc.SpriteFrame","content":{"name":"bg_drop","texture":"c6Cz3Q30JGqbOgTBiuRvtL","rect":[675,0,106,429],"offset":[0,0],"originalSize":[108,435],"capInsets":[0,0,0,0]}},{"__type__":"cc.SpriteFrame","content":{"name":"moregames_hover","texture":"c6Cz3Q30JGqbOgTBiuRvtL","rect":[439,374,76,72],"offset":[0,0],"originalSize":[82,82],"capInsets":[0,0,0,0]}},{"__type__":"cc.SpriteFrame","content":{"name":"btnClose","texture":"c6Cz3Q30JGqbOgTBiuRvtL","rect":[237,446,66,66],"offset":[2,-2],"originalSize":[80,80],"capInsets":[0,0,0,0]}},{"__type__":"cc.EffectAsset","_name":"builtin-2d-sprite","techniques":[{"passes":[{"blendState":{"targets":[{"blend":true}]},"rasterizerState":{"cullMode":0},"program":"builtin-2d-sprite|vs|fs","properties":{"texture":{"value":"white","type":29},"alphaThreshold":{"value":[0.5],"type":13}}}]}],"shaders":[{"hash":4253554819,"glsl3":{"vert":"\nprecision highp float;\nuniform CCGlobal {\n  vec4 cc_time;\n\n  vec4 cc_screenSize;\n\n  vec4 cc_screenScale;\n\n  vec4 cc_nativeSize;\n\n  mat4 cc_matView;\n  mat4 cc_matViewInv;\n  mat4 cc_matProj;\n  mat4 cc_matProjInv;\n  mat4 cc_matViewProj;\n  mat4 cc_matViewProjInv;\n  vec4 cc_cameraPos;\n\n  vec4 cc_exposure;\n\n  vec4 cc_mainLitDir;\n\n  vec4 cc_mainLitColor;\n\n  vec4 cc_ambientSky;\n  vec4 cc_ambientGround;\n};\nuniform CCLocal {\n  mat4 cc_matWorld;\n  mat4 cc_matWorldIT;\n};\n\nin vec3 a_position;\nin vec4 a_color;\nout vec4 v_color;\n\n#if USE_TEXTURE\nin vec2 a_uv0;\nout vec2 v_uv0;\n#endif\n\nvoid main () {\n  vec4 pos = vec4(a_position, 1);\n\n  #if CC_USE_MODEL\n  pos = cc_matViewProj * cc_matWorld * pos;\n  #else\n  pos = cc_matViewProj * pos;\n  #endif\n\n  #if USE_TEXTURE\n  v_uv0 = a_uv0;\n  #endif\n\n  v_color = a_color;\n\n  gl_Position = pos;\n}\n","frag":"\nprecision highp float;\n\n#if USE_ALPHA_TEST\n  \n  uniform ALPHA_TEST {\n    float alphaThreshold;\n  }\n#endif\n\nvoid ALPHA_TEST (in vec4 color) {\n  #if USE_ALPHA_TEST\n      if (color.a < alphaThreshold) discard;\n  #endif\n}\n\nvoid ALPHA_TEST (in float alpha) {\n  #if USE_ALPHA_TEST\n      if (alpha < alphaThreshold) discard;\n  #endif\n}\n\nin vec4 v_color;\n\n#if USE_TEXTURE\nin vec2 v_uv0;\nuniform sampler2D texture;\n#endif\n\nvoid main () {\n  vec4 o = vec4(1, 1, 1, 1);\n\n  #if USE_TEXTURE\n  o *= texture(texture, v_uv0);\n    #if CC_USE_ALPHA_ATLAS_TEXTURE\n    o.a *= texture2D(texture, v_uv0 + vec2(0, 0.5)).r;\n    #endif\n  #endif\n\n  o *= v_color;\n\n  ALPHA_TEST(o);\n\n  gl_FragColor = o;\n}\n"},"glsl1":{"vert":"\nprecision highp float;\nuniform mat4 cc_matViewProj;\nuniform mat4 cc_matWorld;\n\nattribute vec3 a_position;\nattribute vec4 a_color;\nvarying vec4 v_color;\n\n#if USE_TEXTURE\nattribute vec2 a_uv0;\nvarying vec2 v_uv0;\n#endif\n\nvoid main () {\n  vec4 pos = vec4(a_position, 1);\n\n  #if CC_USE_MODEL\n  pos = cc_matViewProj * cc_matWorld * pos;\n  #else\n  pos = cc_matViewProj * pos;\n  #endif\n\n  #if USE_TEXTURE\n  v_uv0 = a_uv0;\n  #endif\n\n  v_color = a_color;\n\n  gl_Position = pos;\n}\n","frag":"\nprecision highp float;\n\n#if USE_ALPHA_TEST\n  \n  uniform float alphaThreshold;\n#endif\n\nvoid ALPHA_TEST (in vec4 color) {\n  #if USE_ALPHA_TEST\n      if (color.a < alphaThreshold) discard;\n  #endif\n}\n\nvoid ALPHA_TEST (in float alpha) {\n  #if USE_ALPHA_TEST\n      if (alpha < alphaThreshold) discard;\n  #endif\n}\n\nvarying vec4 v_color;\n\n#if USE_TEXTURE\nvarying vec2 v_uv0;\nuniform sampler2D texture;\n#endif\n\nvoid main () {\n  vec4 o = vec4(1, 1, 1, 1);\n\n  #if USE_TEXTURE\n  o *= texture2D(texture, v_uv0);\n    #if CC_USE_ALPHA_ATLAS_TEXTURE\n    o.a *= texture2D(texture, v_uv0 + vec2(0, 0.5)).r;\n    #endif\n  #endif\n\n  o *= v_color;\n\n  ALPHA_TEST(o);\n\n  gl_FragColor = o;\n}\n"},"builtins":{"globals":{"blocks":[{"name":"CCGlobal","defines":[]}],"samplers":[]},"locals":{"blocks":[{"name":"CCLocal","defines":[]}],"samplers":[]}},"defines":[{"name":"USE_TEXTURE","type":"boolean","defines":[]},{"name":"CC_USE_MODEL","type":"boolean","defines":[]},{"name":"USE_ALPHA_TEST","type":"boolean","defines":[]},{"name":"CC_USE_ALPHA_ATLAS_TEXTURE","type":"boolean","defines":["USE_TEXTURE"]}],"blocks":[{"name":"ALPHA_TEST","members":[{"name":"alphaThreshold","type":13,"count":1}],"defines":["USE_ALPHA_TEST"],"binding":0}],"samplers":[{"name":"texture","type":29,"count":1,"defines":["USE_TEXTURE"],"binding":30}],"dependencies":{},"name":"builtin-2d-sprite|vs|fs"}]},{"__type__":"cc.SpriteFrame","content":{"name":"btnClose_hover","texture":"c6Cz3Q30JGqbOgTBiuRvtL","rect":[783,284,60,60],"offset":[2,-2],"originalSize":[80,80],"capInsets":[0,0,0,0]}},{"__type__":"cc.SpriteFrame","content":{"name":"btnWifiVS_hover_EN","texture":"c6Cz3Q30JGqbOgTBiuRvtL","rect":[0,246,297,44],"offset":[0,2],"originalSize":[301,70],"capInsets":[0,0,0,0]}},{"__type__":"cc.SpriteFrame","content":{"name":"btnGameSingle_hover_CN","texture":"c6Cz3Q30JGqbOgTBiuRvtL","rect":[299,254,235,58],"offset":[2,0],"originalSize":[301,70],"capInsets":[0,0,0,0]}},{"__type__":"cc.Texture2D","content":"0,9729,9729,33071,33071,0,0,1"},{"__type__":"cc.SpriteFrame","content":{"name":"btnWifiVS_hover_CN","texture":"c6Cz3Q30JGqbOgTBiuRvtL","rect":[0,430,235,58],"offset":[2,0],"originalSize":[301,70],"capInsets":[0,0,0,0]}},{"__type__":"cc.SpriteFrame","content":{"name":"share","texture":"f7mK3ziVJPA5j3i315JZ5M","rect":[16,12,507,71],"offset":[-4,-1],"originalSize":[547,93],"capInsets":[0,0,0,0]}},{"__type__":"cc.SpriteFrame","content":{"name":"btnDrop","texture":"c6Cz3Q30JGqbOgTBiuRvtL","rect":[517,410,74,74],"offset":[0,0],"originalSize":[80,80],"capInsets":[0,0,0,0]}},{"__type__":"cc.SpriteFrame","content":{"name":"btnWifiVS_CN","texture":"c6Cz3Q30JGqbOgTBiuRvtL","rect":[415,194,235,58],"offset":[2,0],"originalSize":[301,70],"capInsets":[0,0,0,0]}},{"__type__":"cc.SpriteFrame","content":{"name":"btnArrowLeft_hover","texture":"c6Cz3Q30JGqbOgTBiuRvtL","rect":[783,214,60,68],"offset":[0,-1],"originalSize":[60,70],"capInsets":[0,0,0,0]}},{"__type__":"cc.SpriteFrame","content":{"name":"playgameNormal","texture":"18eqfoTUxDG611sNfEl//s","rect":[0,0,167,38],"offset":[0,0],"originalSize":[167,38],"capInsets":[0,0,0,0]}},{"__type__":"cc.SpriteAtlas","_name":"menuscene.plist","_spriteFrames":{"bg_drop":{"__uuid__":"2123vUgQpD5bX4vQkxbEQu"},"btnArrowLeft":{"__uuid__":"74leVVmcZJ5KPuRBXq5lb9"},"btnArrowLeft_hover":{"__uuid__":"53b+J2ATJN9LPSi1zlS8Xi"},"btnArrowRight":{"__uuid__":"1eZAem3BFKrr+4kYbKvT3e"},"btnArrowRight_hover":{"__uuid__":"7f1gTUcp5NX6vBnXkBUGMw"},"btnClose":{"__uuid__":"26hMrcBkhBvL+yynwwDZP/"},"btnClose_hover":{"__uuid__":"35aGNBGgpPjYdYpmqlhHG6"},"btnDrop":{"__uuid__":"51jyY+4KNEkYX9A01OLRWg"},"btnDrop_hover":{"__uuid__":"84waHs2tlFAorknKC99fw5"},"btnForbidSign":{"__uuid__":"d4LX+Nqf5FUonmiyewoC0/"},"btnGameSingle_CN":{"__uuid__":"bfVFqZo1FE7LlAK2zh4oTP"},"btnGameSingle_EN":{"__uuid__":"adM9fbbN9Mv6OTw+21A+zG"},"btnGameSingle_hover_CN":{"__uuid__":"42hBIlJUpNHZXKQ+UztlaL"},"btnGameSingle_hover_EN":{"__uuid__":"015IsQKe5Ff4UrAJZeRsJH"},"btnMusic":{"__uuid__":"0chFleSwNA3LzMy2wFZh6B"},"btnMusic_hover":{"__uuid__":"c39wPb+cVA977eJrHnFt3x"},"btnSound":{"__uuid__":"deXvUev4NFz6ENloyTgi9Z"},"btnSound_hover":{"__uuid__":"14Q771quBBKLf8W1gkBpyy"},"btnWifiVS_CN":{"__uuid__":"52vANdMVdMUI+in4x30Wt2"},"btnWifiVS_EN":{"__uuid__":"06hv75bKFGe7M6zptMb4Gn"},"btnWifiVS_hover_CN":{"__uuid__":"481i6fAr5EiqGPwJQMeXqi"},"btnWifiVS_hover_EN":{"__uuid__":"36EerF/OxPe7jcQyrb0y65"},"game_title_CN":{"__uuid__":"17meXqdJNEQIjhbEdjE2ig"},"game_title_EN":{"__uuid__":"b9L6N/+LtHh7RXdHaod8Lw"},"level_CN":{"__uuid__":"ffLxisuoRAdoKsXyt2Oqxz"},"level_EN":{"__uuid__":"e5LhJqNqNH8ZRig16HzRKP"},"moregames":{"__uuid__":"21tuaPKBdKt62FvWLmCFEQ"},"moregames_hover":{"__uuid__":"2462f44aJB/K96zLOlaMdJ"},"rank":{"__uuid__":"da99Fi9O5DyL7bBfjW9a+g"},"rank_hover":{"__uuid__":"03XlTlAdhE96AVSdEuaj/z"}}},{"__type__":"cc.SpriteFrame","content":{"name":"btnArrowLeft","texture":"c6Cz3Q30JGqbOgTBiuRvtL","rect":[783,72,60,70],"offset":[0,0],"originalSize":[60,70],"capInsets":[0,0,0,0]}},{"__type__":"cc.Texture2D","content":"0,9729,9729,33071,33071,0,0,1"},{"__type__":"cc.SpriteFrame","content":{"name":"btnArrowRight_hover","texture":"c6Cz3Q30JGqbOgTBiuRvtL","rect":[783,144,60,68],"offset":[0,-1],"originalSize":[60,70],"capInsets":[0,0,0,0]}},{"__type__":"cc.SpriteFrame","content":{"name":"btnDrop_hover","texture":"c6Cz3Q30JGqbOgTBiuRvtL","rect":[593,410,68,68],"offset":[0,0],"originalSize":[80,80],"capInsets":[0,0,0,0]}},{"__type__":"cc.SpriteFrame","content":{"name":"btnGameSingle_EN","texture":"c6Cz3Q30JGqbOgTBiuRvtL","rect":[0,384,281,44],"offset":[2,2],"originalSize":[301,70],"capInsets":[0,0,0,0]}},{"__type__":"cc.SpriteFrame","content":{"name":"game_title_EN","texture":"c6Cz3Q30JGqbOgTBiuRvtL","rect":[0,96,661,96],"offset":[2,1],"originalSize":[681,120],"capInsets":[0,0,0,0]}},{"__type__":"cc.SpriteFrame","content":{"name":"btnGameSingle_CN","texture":"c6Cz3Q30JGqbOgTBiuRvtL","rect":[299,314,235,58],"offset":[2,0],"originalSize":[301,70],"capInsets":[0,0,0,0]}},{"__type__":"cc.SpriteFrame","content":{"name":"ScenceStart","texture":"46PiPv3rdJ65jxXdrYYYtb","rect":[0,0,600,400],"offset":[0,0],"originalSize":[600,400],"capInsets":[0,0,0,0]}},{"__type__":"cc.SpriteFrame","content":{"name":"btnMusic_hover","texture":"c6Cz3Q30JGqbOgTBiuRvtL","rect":[743,431,62,60],"offset":[0,-2],"originalSize":[80,80],"capInsets":[0,0,0,0]}},{"__type__":"cc.Texture2D","content":"0,9729,9729,33071,33071,0,0,1"},{"__type__":"cc.SpriteFrame","content":{"name":"blank","texture":"f0L6vR2b1Nja5GunOX8JXE","rect":[0,0,32,32],"offset":[0,0],"originalSize":[32,32],"capInsets":[0,0,0,0]}},[{"__type__":"cc.SceneAsset","_name":"home_scene","scene":{"__id__":1},"asyncLoadAssets":null},{"__type__":"cc.Scene","_name":"New Node","_children":[{"__id__":2}],"_active":false,"_anchorPoint":{"__type__":"cc.Vec2"},"_trs":{"__type__":"TypedArray","ctor":"Float64Array","array":[0,0,0,0,0,0,1,1,1,1]},"autoReleaseAssets":false},{"__type__":"cc.Node","_name":"Canvas","_parent":{"__id__":1},"_children":[{"__id__":3},{"__id__":4},{"__id__":6},{"__id__":7},{"__id__":8},{"__id__":10}],"_components":[{"__type__":"cc.Canvas","node":{"__id__":2},"_designResolution":{"__type__":"cc.Size","width":1334,"height":750}}],"_contentSize":{"__type__":"cc.Size","width":1334,"height":750},"_trs":{"__type__":"TypedArray","ctor":"Float64Array","array":[667,375,0,0,0,0,1,1,1,1]},"_id":"9dGtjbJwJIX5s4z02XqyxS"},{"__type__":"cc.Node","_name":"Main Camera","_parent":{"__id__":2},"_components":[{"__type__":"cc.Camera","node":{"__id__":3},"_clearFlags":7,"_backgroundColor":{"__type__":"cc.Color","r":126,"g":126,"b":126},"_depth":-1}],"_trs":{"__type__":"TypedArray","ctor":"Float64Array","array":[0,0,0,0,0,0,1,1,1,1]}},{"__type__":"cc.Node","_name":"bg","_parent":{"__id__":2},"_children":[{"__id__":5}],"_components":[{"__type__":"cc.Sprite","node":{"__id__":4},"_materials":[{"__uuid__":"ecpdLyjvZBwrvm+cedCcQy"}],"_spriteFrame":{"__uuid__":"ceOZcHWnVNVqqPeBZ7U/rl"},"_sizeMode":0},{"__type__":"cc.Widget","node":{"__id__":4},"_alignFlags":45,"_originalWidth":32,"_originalHeight":32}],"_contentSize":{"__type__":"cc.Size","width":1334,"height":750},"_trs":{"__type__":"TypedArray","ctor":"Float64Array","array":[0,0,0,0,0,0,1,1,1,1]}},{"__type__":"cc.Node","_name":"title","_parent":{"__id__":4},"_components":[{"__type__":"cc.Sprite","node":{"__id__":5},"_materials":[{"__uuid__":"ecpdLyjvZBwrvm+cedCcQy"}],"_spriteFrame":{"__uuid__":"17meXqdJNEQIjhbEdjE2ig"}},{"__type__":"cc.Widget","node":{"__id__":5},"_alignFlags":17,"_top":150}],"_contentSize":{"__type__":"cc.Size","width":673,"height":94},"_trs":{"__type__":"TypedArray","ctor":"Float64Array","array":[0,178,0,0,0,0,1,1,1,1]}},{"__type__":"cc.Node","_name":"ScenceStart","_parent":{"__id__":2},"_active":false,"_components":[{"__type__":"cc.Sprite","node":{"__id__":6},"_materials":[{"__uuid__":"ecpdLyjvZBwrvm+cedCcQy"}],"_spriteFrame":{"__uuid__":"c3GA1dXRlI+77NsYUk+CHc"},"_sizeMode":0},{"__type__":"cc.Widget","node":{"__id__":6},"_alignFlags":45,"_originalWidth":600,"_originalHeight":400}],"_contentSize":{"__type__":"cc.Size","width":600,"height":416},"_trs":{"__type__":"TypedArray","ctor":"Float64Array","array":[0,0,0,0,0,0,1,1,1,1]}},{"__type__":"cc.Node","_name":"share","_parent":{"__id__":2},"_active":false,"_components":[{"__type__":"cc.Sprite","node":{"__id__":7},"_materials":[{"__uuid__":"ecpdLyjvZBwrvm+cedCcQy"}],"_spriteFrame":{"__uuid__":"4fwpprNKpPTZ9u22nmMcDP"}},{"__type__":"cc.Widget","node":{"__id__":7},"_alignFlags":18,"_verticalCenter":-70}],"_contentSize":{"__type__":"cc.Size","width":507,"height":71},"_trs":{"__type__":"TypedArray","ctor":"Float64Array","array":[0,-70,0,0,0,0,1,0.4,0.4,1]}},{"__type__":"cc.Node","_name":"start","_parent":{"__id__":2},"_children":[{"__id__":9}],"_components":[{"__type__":"cc.Button","node":{"__id__":8},"clickEvents":[{"__type__":"cc.ClickEvent","target":{"__id__":10},"_componentId":"a1fc5/XUiJJF4/aBhASml/p","handler":"onClickBtn"}],"_N$transition":2,"transition":2,"_N$normalColor":{"__type__":"cc.Color","r":230,"g":230,"b":230},"_N$pressedColor":{"__type__":"cc.Color","r":200,"g":200,"b":200},"pressedColor":{"__type__":"cc.Color","r":200,"g":200,"b":200},"_N$disabledColor":{"__type__":"cc.Color","r":120,"g":120,"b":120,"a":200},"_N$normalSprite":{"__uuid__":"e34J3e2mVABpzYE66zyijX"},"_N$pressedSprite":{"__uuid__":"5a9sqGi/NE1pxFyH5t3we9"},"pressedSprite":{"__uuid__":"5a9sqGi/NE1pxFyH5t3we9"},"_N$hoverSprite":{"__uuid__":"e34J3e2mVABpzYE66zyijX"},"hoverSprite":{"__uuid__":"e34J3e2mVABpzYE66zyijX"},"_N$disabledSprite":{"__uuid__":"5a9sqGi/NE1pxFyH5t3we9"},"_N$target":{"__id__":9}},{"__type__":"cc.Widget","node":{"__id__":8},"_alignFlags":20,"_bottom":150}],"_contentSize":{"__type__":"cc.Size","width":167,"height":38},"_trs":{"__type__":"TypedArray","ctor":"Float64Array","array":[0,-177.5,0,0,0,0,1,2.5,2.5,1]}},{"__type__":"cc.Node","_name":"Background","_parent":{"__id__":8},"_components":[{"__type__":"cc.Sprite","node":{"__id__":9},"_materials":[{"__uuid__":"ecpdLyjvZBwrvm+cedCcQy"}],"_spriteFrame":{"__uuid__":"e34J3e2mVABpzYE66zyijX"},"_type":1,"_sizeMode":0},{"__type__":"cc.Widget","node":{"__id__":9},"alignMode":0,"_alignFlags":45,"_originalWidth":100,"_originalHeight":40}],"_color":{"__type__":"cc.Color","r":230,"g":230,"b":230},"_contentSize":{"__type__":"cc.Size","width":167,"height":38},"_trs":{"__type__":"TypedArray","ctor":"Float64Array","array":[0,0,0,0,0,0,1,1,1,1]}},{"__type__":"cc.Node","_name":"control","_parent":{"__id__":2},"_components":[{"__type__":"a1fc5/XUiJJF4/aBhASml/p","node":{"__id__":10}}],"_trs":{"__type__":"TypedArray","ctor":"Float64Array","array":[0,0,0,0,0,0,1,1,1,1]}}],{"__type__":"cc.SpriteFrame","content":{"name":"btnForbidSign","texture":"c6Cz3Q30JGqbOgTBiuRvtL","rect":[447,448,68,58],"offset":[2,-2],"originalSize":[80,80],"capInsets":[0,0,0,0]}},{"__type__":"cc.SpriteFrame","content":{"name":"rank","texture":"c6Cz3Q30JGqbOgTBiuRvtL","rect":[536,254,80,76],"offset":[0,0],"originalSize":[82,82],"capInsets":[0,0,0,0]}},{"__type__":"cc.SpriteFrame","content":{"name":"btnSound","texture":"c6Cz3Q30JGqbOgTBiuRvtL","rect":[283,374,76,70],"offset":[0,0],"originalSize":[80,80],"capInsets":[0,0,0,0]}},{"__type__":"cc.SpriteFrame","content":{"name":"playgameClose","texture":"7fcTDmAhJFk6xBvSei0Qer","rect":[0,0,167,38],"offset":[0,0],"originalSize":[167,38],"capInsets":[0,0,0,0]}},{"__type__":"cc.SpriteFrame","content":{"name":"level_EN","texture":"c6Cz3Q30JGqbOgTBiuRvtL","rect":[663,431,78,40],"offset":[-186,3],"originalSize":[450,56],"capInsets":[0,0,0,0]}},{"__type__":"cc.Material","_name":"builtin-2d-sprite","_effectAsset":{"__uuid__":"28dPjdQWxEQIG3VVl1Qm6T"},"_defines":{"USE_TEXTURE":true},"_props":{}},{"__type__":"cc.Texture2D","content":"0,9729,9729,33071,33071,0,0,1"},{"__type__":"cc.Texture2D","content":"0,9729,9729,33071,33071,0,0,1"},{"__type__":"cc.SpriteFrame","content":{"name":"level_CN","texture":"c6Cz3Q30JGqbOgTBiuRvtL","rect":[0,194,413,50],"offset":[-2,1],"originalSize":[431,56],"capInsets":[0,0,0,0]}}]